GoodByeSyntax/__init__.py
GoodByeSyntax/module.py
goodbyesyntax-1.6.dist-info/LICENSE
goodbyesyntax-1.6.dist-info/METADATA
goodbyesyntax-1.6.dist-info/WHEEL
goodbyesyntax-1.6.dist-info/top_level.txt
goodbyesyntax-1.6.dist-info/RECORD
