Metadata-Version: 2.2
Name: GoodByeSyntax
Version: 1.6
Summary: GoodByeSyntax Python Module
Home-page: https://github.com/GoodByeSyntax/GBS
Author: GoodByeSyntax
Author-email: goodbyesyntax.official@gmail.com
Classifier: Programming Language :: Python :: 3
Classifier: License :: OSI Approved :: MIT License
Classifier: Intended Audience :: Developers
License-File: LICENSE
Dynamic: author
Dynamic: author-email
Dynamic: classifier
Dynamic: description
Dynamic: description-content-type
Dynamic: home-page
Dynamic: summary
